jaraco/tidelift/__init__.py
jaraco/tidelift/banner.html
jaraco/tidelift/banner.py
jaraco/tidelift/publish-release-notes.py
jaraco.tidelift-1.5.0.dist-info/LICENSE
jaraco.tidelift-1.5.0.dist-info/METADATA
jaraco.tidelift-1.5.0.dist-info/WHEEL
jaraco.tidelift-1.5.0.dist-info/top_level.txt
jaraco.tidelift-1.5.0.dist-info/RECORD
